{
    "level":
    {
        "bgImage" : "images/backgrounds/bg_flat.png",
        "tileSet" : "images/basetileset.png",
        "tileWidth":64,
        "tileHeight":64,
        "tileFPL":16,
        "tileMap":[
            [1,1,1,1,1,2,1,1,1,1,1,1,1,1,1,1,1,1,1,1,1,1,1,1,1,1,1,1,1,1,1,1],
            [2,1,1,1,1,1,1,1,2,1,1,1,1,1,1,1,3,1,1,1,1,1,1,1,1,1,1,1,1,1,1,1],
            [1,1,1,4,1,1,1,1,1,1,1,1,1,3,1,1,1,1,1,1,1,2,1,1,1,2,1,1,1,1,1,1],
            [1,1,1,1,2,1,1,1,1,4,1,1,1,1,1,1,1,1,1,2,1,1,1,1,1,1,1,1,1,1,2,1],
            [1,1,1,1,1,1,1,1,1,1,1,1,1,1,2,1,1,1,1,1,1,1,1,1,4,1,1,1,1,1,1,1],
            [1,1,1,1,1,1,1,1,1,1,1,1,1,1,1,1,1,1,1,1,1,1,1,1,1,1,1,1,1,1,1,1],
            [1,1,1,1,3,1,1,2,1,1,4,1,1,1,1,1,1,1,1,1,1,2,1,2,1,1,1,1,3,1,1,1],
            [1,2,1,1,1,1,2,1,1,1,1,1,1,1,1,1,1,2,1,1,1,1,1,1,1,2,1,1,1,1,1,1],
            [1,1,1,1,2,1,1,1,1,1,1,1,1,1,1,1,1,1,1,1,1,1,1,1,1,1,2,1,1,4,1,1],
            [1,1,1,1,1,1,1,1,1,1,1,3,1,1,1,2,1,1,1,2,1,1,2,1,1,1,1,1,1,1,1,1],
            [1,1,1,1,1,1,1,1,1,1,1,1,1,2,1,1,1,1,4,1,1,1,1,1,1,2,1,1,1,1,1,1],
            [1,1,4,1,1,1,2,1,2,1,1,1,1,1,1,1,1,1,1,1,1,1,1,1,1,1,1,1,2,1,1,1],
            [1,1,1,1,2,1,1,1,1,1,1,1,1,1,1,1,1,1,1,1,2,1,1,1,1,1,1,1,1,1,1,1],
            [1,1,1,1,1,1,2,1,1,1,1,1,1,1,1,1,1,1,1,1,1,1,2,1,1,1,1,1,1,1,1,1],
            [1,2,1,1,1,1,1,1,1,1,1,2,1,1,1,3,1,1,1,1,1,1,1,1,1,1,1,4,1,1,2,1],
            [1,1,1,1,1,1,1,1,1,1,1,1,1,1,1,1,1,1,1,1,1,1,1,1,1,1,1,1,1,1,1,1]
        ]
    }
}